wordnet_db_migrator/__init__.py
wordnet_db_migrator/bootstrap.py
wordnet_db_migrator/cli.py
wordnet_db_migrator/config.py
wordnet_db_migrator/main.py
wordnet_db_migrator/test_config.py
wordnet_db_migrator/steps/__init__.py
wordnet_db_migrator/steps/step010_test_sqlite_connection.py
wordnet_db_migrator/steps/step020_postgres_credentials.py
wordnet_db_migrator/steps/step030_create_postgres_database.py
wordnet_db_migrator/steps/step035_purge_directories.py
wordnet_db_migrator/steps/step040_extract_sqlite_schema.py
wordnet_db_migrator/steps/step045_analyze_dependencies.py
wordnet_db_migrator/steps/step050_extract_sqlite_metadata.py
wordnet_db_migrator/steps/step060_generate_tables.py
wordnet_db_migrator/steps/step065_generate_foreign_keys.py
wordnet_db_migrator/steps/step067_generate_foreign_key_validators.py
wordnet_db_migrator/steps/step068_generate_indexes.py
wordnet_db_migrator/steps/step070_run_table_scripts.py
wordnet_db_migrator/steps/step080_run_index_scripts.py
wordnet_db_migrator/steps/step090_insert_data_tables.py
wordnet_db_migrator/steps/step095_validate_foreign_key_data.py
wordnet_db_migrator/steps/step100_apply_foreign_keys.py
wordnet_db_migrator/tests/__init__.py
wordnet_db_migrator/tests/conftest.py
wordnet_db_migrator/tests/test_config.py
wordnet_db_migrator/utils/__init__.py
wordnet_db_migrator/utils/db_utils.py
wordnet_db_migrator-1.0.0.dist-info/licenses/LICENSE
wordnet_db_migrator-1.0.0.dist-info/METADATA
wordnet_db_migrator-1.0.0.dist-info/WHEEL
wordnet_db_migrator-1.0.0.dist-info/entry_points.txt
wordnet_db_migrator-1.0.0.dist-info/top_level.txt
wordnet_db_migrator-1.0.0.dist-info/RECORD
