Metadata-Version: 2.4
Name: wordnet_db_migrator
Version: 1.0.0
Summary: A utility to migrate WordNet database from SQLite to PostgreSQL
Home-page: https://github.com/onareach/wordnet_db_migrator
Author: David Long
Author-email: David Long <davidlong@unr.edu>
License: MIT
Project-URL: Bug Reports, https://github.com/onareach/wordnet_db_migrator/issues
Project-URL: Source, https://github.com/onareach/wordnet_db_migrator
Keywords: wordnet,postgresql,sqlite,migration
Classifier: Development Status :: 3 - Alpha
Classifier: Intended Audience :: Developers
Classifier: Topic :: Database
Classifier: Programming Language :: Python :: 3
Classifier: Programming Language :: Python :: 3.6
Classifier: Programming Language :: Python :: 3.7
Classifier: Programming Language :: Python :: 3.8
Classifier: Programming Language :: Python :: 3.9
Classifier: Programming Language :: Python :: 3.10
Classifier: Programming Language :: Python :: 3.11
Requires-Python: >=3.6, <4
License-File: LICENSE
Requires-Dist: psycopg2-binary>=2.9.3
Requires-Dist: pyyaml>=6.0
Requires-Dist: tqdm>=4.62.0
Requires-Dist: pathlib>=1.0.1; python_version < "3.4"
Provides-Extra: dev
Requires-Dist: pytest>=7.0.0; extra == "dev"
Requires-Dist: black>=22.1.0; extra == "dev"
Requires-Dist: flake8>=4.0.1; extra == "dev"
Requires-Dist: isort>=5.9.1; extra == "dev"
Requires-Dist: mypy>=0.812; extra == "dev"
Requires-Dist: build>=0.7.0; extra == "dev"
Requires-Dist: twine>=3.4.2; extra == "dev"
Provides-Extra: data
Requires-Dist: pandas>=1.3.5; extra == "data"
Requires-Dist: numpy>=1.21.5; extra == "data"
Provides-Extra: docs
Requires-Dist: mkdocs>=1.3.0; extra == "docs"
Requires-Dist: mkdocs-material>=8.2.0; extra == "docs"
Requires-Dist: pymdown-extensions>=9.0; extra == "docs"
Dynamic: author
Dynamic: classifier
Dynamic: home-page
Dynamic: keywords
Dynamic: license-file
Dynamic: project-url
Dynamic: provides-extra
Dynamic: requires-dist
Dynamic: requires-python
